pylite/__init__.py
pylite/simplite.py
pylite-0.1.0.dist-info/LICENSE.txt
pylite-0.1.0.dist-info/METADATA
pylite-0.1.0.dist-info/WHEEL
pylite-0.1.0.dist-info/top_level.txt
pylite-0.1.0.dist-info/RECORD
