Metadata-Version: 2.1
Name: pylite
Version: 0.1.0
Summary: Intract with sqlite3 in python as simple as it can be.
Home-page: http://dariubs.github.io/pylite
Author: Dariush Abbasi
Author-email: poshtehani@gmail.com
License: MIT
Platform: UNKNOWN
Classifier: Programming Language :: Python :: 3
Classifier: License :: OSI Approved :: MIT License
Classifier: Operating System :: OS Independent
